PyRayHF/__init__.py
PyRayHF/library.py
PyRayHF/tests/test_core.py
pyrayhf-0.0.2.dist-info/licenses/LICENSE
pyrayhf-0.0.2.dist-info/METADATA
pyrayhf-0.0.2.dist-info/WHEEL
pyrayhf-0.0.2.dist-info/top_level.txt
pyrayhf-0.0.2.dist-info/RECORD
