Metadata-Version: 2.4
Name: PyRayHF
Version: 0.0.2
Summary: Python HF Raytracing for Ionosphere
Author-email: Victoriya Forsythe <victoriya.v.makarevich.civ@us.navy.mil>
License: MIT License
Project-URL: Documentation, https://PyRayHF.readthedocs.io/en/latest/
Project-URL: Source, https://github.com/victoriyaforsythe/PyRayHF
Keywords: ionosphere,raytracing,modelling
Classifier: Development Status :: 3 - Alpha
Classifier: Topic :: Scientific/Engineering :: Physics
Classifier: Topic :: Scientific/Engineering :: Atmospheric Science
Classifier: Intended Audience :: Science/Research
Classifier: License :: OSI Approved :: BSD License
Classifier: Natural Language :: English
Classifier: Programming Language :: Python :: 3
Classifier: Programming Language :: Python :: 3.9
Classifier: Programming Language :: Python :: 3.10
Classifier: Programming Language :: Python :: 3.11
Classifier: Programming Language :: Python :: 3.12
Classifier: Programming Language :: Python :: 3.13
Classifier: Operating System :: POSIX :: Linux
Classifier: Operating System :: MacOS :: MacOS X
Classifier: Operating System :: Microsoft :: Windows
Requires-Python: >=3.9
License-File: LICENSE
Requires-Dist: lmfit
Requires-Dist: numpy
Requires-Dist: PyIRI
Requires-Dist: pytest
Provides-Extra: test
Requires-Dist: coveralls; extra == "test"
Requires-Dist: flake8; extra == "test"
Requires-Dist: flake8-docstrings; extra == "test"
Requires-Dist: hacking>=1.0; extra == "test"
Requires-Dist: pytest; extra == "test"
Requires-Dist: pytest-cov; extra == "test"
Provides-Extra: doc
Requires-Dist: extras_require; extra == "doc"
Requires-Dist: ipython; extra == "doc"
Requires-Dist: myst_parser; extra == "doc"
Requires-Dist: numpydoc; extra == "doc"
Requires-Dist: sphinx; extra == "doc"
Requires-Dist: sphinx_rtd_theme; extra == "doc"
Dynamic: license-file
